{
  "HTTP GET Request 9wait for result" : {
    "transaction" : "HTTP GET Request 9wait for result",
    "sampleCount" : 3,
    "errorCount" : 0,
    "errorPct" : 0.0,
    "meanResTime" : 287.0,
    "medianResTime" : 285.0,
    "minResTime" : 277.0,
    "maxResTime" : 299.0,
    "pct1ResTime" : 299.0,
    "pct2ResTime" : 299.0,
    "pct3ResTime" : 299.0,
    "throughput" : 3.260869565217391,
    "receivedKBytesPerSec" : 5.043096127717391,
    "sentKBytesPerSec" : 1.5253481657608694
  },
  "HTTP GET Request 9 for result" : {
    "transaction" : "HTTP GET Request 9 for result",
    "sampleCount" : 4,
    "errorCount" : 0,
    "errorPct" : 0.0,
    "meanResTime" : 422.25,
    "medianResTime" : 293.5,
    "minResTime" : 271.0,
    "maxResTime" : 831.0,
    "pct1ResTime" : 831.0,
    "pct2ResTime" : 831.0,
    "pct3ResTime" : 831.0,
    "throughput" : 0.059312860510980295,
    "receivedKBytesPerSec" : 0.07770332263230476,
    "sentKBytesPerSec" : 0.028903434956034344
  },
  "NEW_DAILY_VLN - HTTP POST Request 82 for running query" : {
    "transaction" : "NEW_DAILY_VLN - HTTP POST Request 82 for running query",
    "sampleCount" : 4,
    "errorCount" : 0,
    "errorPct" : 0.0,
    "meanResTime" : 925.5000000000001,
    "medianResTime" : 489.5,
    "minResTime" : 374.0,
    "maxResTime" : 2349.0,
    "pct1ResTime" : 2349.0,
    "pct2ResTime" : 2349.0,
    "pct3ResTime" : 2349.0,
    "throughput" : 0.04971661529283086,
    "receivedKBytesPerSec" : 0.06947702781644625,
    "sentKBytesPerSec" : 0.02786849333797355
  },
  "HTTP GET Request 6 for result" : {
    "transaction" : "HTTP GET Request 6 for result",
    "sampleCount" : 4,
    "errorCount" : 0,
    "errorPct" : 0.0,
    "meanResTime" : 797.0,
    "medianResTime" : 857.5,
    "minResTime" : 271.0,
    "maxResTime" : 1202.0,
    "pct1ResTime" : 1202.0,
    "pct2ResTime" : 1202.0,
    "pct3ResTime" : 1202.0,
    "throughput" : 0.05509414211533959,
    "receivedKBytesPerSec" : 0.0722572586532237,
    "sentKBytesPerSec" : 0.02684763370659615
  },
  "HTTP POST Request 14 for running query" : {
    "transaction" : "HTTP POST Request 14 for running query",
    "sampleCount" : 3,
    "errorCount" : 0,
    "errorPct" : 0.0,
    "meanResTime" : 549.3333333333334,
    "medianResTime" : 349.0,
    "minResTime" : 306.0,
    "maxResTime" : 993.0,
    "pct1ResTime" : 993.0,
    "pct2ResTime" : 993.0,
    "pct3ResTime" : 993.0,
    "throughput" : 0.0777343041484207,
    "receivedKBytesPerSec" : 0.11569050734589173,
    "sentKBytesPerSec" : 0.04957080137589718
  },
  "COMPLIANCE_SUNBURST - HTTP POST Request 92 for running query" : {
    "transaction" : "COMPLIANCE_SUNBURST - HTTP POST Request 92 for running query",
    "sampleCount" : 6,
    "errorCount" : 0,
    "errorPct" : 0.0,
    "meanResTime" : 1074.1666666666667,
    "medianResTime" : 386.5,
    "minResTime" : 304.0,
    "maxResTime" : 4463.0,
    "pct1ResTime" : 4463.0,
    "pct2ResTime" : 4463.0,
    "pct3ResTime" : 4463.0,
    "throughput" : 0.0652507259143258,
    "receivedKBytesPerSec" : 0.09164201072830686,
    "sentKBytesPerSec" : 0.03791424015529673
  },
  "COMPLIANCE_STANDARDS - HTTP POST Request 96wait for result" : {
    "transaction" : "COMPLIANCE_STANDARDS - HTTP POST Request 96wait for result",
    "sampleCount" : 2,
    "errorCount" : 0,
    "errorPct" : 0.0,
    "meanResTime" : 290.0,
    "medianResTime" : 290.0,
    "minResTime" : 282.0,
    "maxResTime" : 298.0,
    "pct1ResTime" : 298.0,
    "pct2ResTime" : 298.0,
    "pct3ResTime" : 298.0,
    "throughput" : 3.3670033670033668,
    "receivedKBytesPerSec" : 4.463581123737374,
    "sentKBytesPerSec" : 2.03861531986532
  },
  "HTTP POST Request 6 for running query" : {
    "transaction" : "HTTP POST Request 6 for running query",
    "sampleCount" : 4,
    "errorCount" : 0,
    "errorPct" : 0.0,
    "meanResTime" : 447.5,
    "medianResTime" : 419.0,
    "minResTime" : 328.0,
    "maxResTime" : 624.0,
    "pct1ResTime" : 624.0,
    "pct2ResTime" : 624.0,
    "pct3ResTime" : 624.0,
    "throughput" : 0.055026687943652675,
    "receivedKBytesPerSec" : 0.08757787566032027,
    "sentKBytesPerSec" : 0.04352696995542839
  },
  "COMPLIANCE_FAILED_RULES_BY_STANDARDS - HTTP POST Request 97 wait for result" : {
    "transaction" : "COMPLIANCE_FAILED_RULES_BY_STANDARDS - HTTP POST Request 97 wait for result",
    "sampleCount" : 2,
    "errorCount" : 0,
    "errorPct" : 0.0,
    "meanResTime" : 294.0,
    "medianResTime" : 294.0,
    "minResTime" : 294.0,
    "maxResTime" : 294.0,
    "pct1ResTime" : 294.0,
    "pct2ResTime" : 294.0,
    "pct3ResTime" : 294.0,
    "throughput" : 3.246753246753247,
    "receivedKBytesPerSec" : 4.305752840909091,
    "sentKBytesPerSec" : 2.0197088068181817
  },
  "TOP_NONCOMPLIANT_ASSETS - HTTP POST Request 99 for running query" : {
    "transaction" : "TOP_NONCOMPLIANT_ASSETS - HTTP POST Request 99 for running query",
    "sampleCount" : 5,
    "errorCount" : 0,
    "errorPct" : 0.0,
    "meanResTime" : 848.4,
    "medianResTime" : 391.0,
    "minResTime" : 354.0,
    "maxResTime" : 2650.0,
    "pct1ResTime" : 2650.0,
    "pct2ResTime" : 2650.0,
    "pct3ResTime" : 2650.0,
    "throughput" : 0.0879445597495339,
    "receivedKBytesPerSec" : 0.12186848660604355,
    "sentKBytesPerSec" : 0.05049941516867767
  },
  "HTTP POST Request 13 for running query" : {
    "transaction" : "HTTP POST Request 13 for running query",
    "sampleCount" : 3,
    "errorCount" : 0,
    "errorPct" : 0.0,
    "meanResTime" : 2051.3333333333335,
    "medianResTime" : 2681.0,
    "minResTime" : 379.0,
    "maxResTime" : 3094.0,
    "pct1ResTime" : 3094.0,
    "pct2ResTime" : 3094.0,
    "pct3ResTime" : 3094.0,
    "throughput" : 0.06781653367090897,
    "receivedKBytesPerSec" : 0.10768523803603318,
    "sentKBytesPerSec" : 0.053312802348712614
  },
  "COMPLIANCE_TREND - HTTP POST Request 95 wait for result" : {
    "transaction" : "COMPLIANCE_TREND - HTTP POST Request 95 wait for result",
    "sampleCount" : 3,
    "errorCount" : 0,
    "errorPct" : 0.0,
    "meanResTime" : 1924.0,
    "medianResTime" : 1146.0,
    "minResTime" : 287.0,
    "maxResTime" : 4339.0,
    "pct1ResTime" : 4339.0,
    "pct2ResTime" : 4339.0,
    "pct3ResTime" : 4339.0,
    "throughput" : 0.513347022587269,
    "receivedKBytesPerSec" : 0.6889745358487337,
    "sentKBytesPerSec" : 0.31131689553388087
  },
  "HTTP POST Request 5 for running query" : {
    "transaction" : "HTTP POST Request 5 for running query",
    "sampleCount" : 4,
    "errorCount" : 0,
    "errorPct" : 0.0,
    "meanResTime" : 2119.5,
    "medianResTime" : 1579.5,
    "minResTime" : 381.0,
    "maxResTime" : 4938.0,
    "pct1ResTime" : 4938.0,
    "pct2ResTime" : 4938.0,
    "pct3ResTime" : 4938.0,
    "throughput" : 0.05110253724097401,
    "receivedKBytesPerSec" : 0.08129495426322916,
    "sentKBytesPerSec" : 0.04042290543475484
  },
  "COMPLIANCE_SUNBURST - HTTP POST Request 91wait for result" : {
    "transaction" : "COMPLIANCE_SUNBURST - HTTP POST Request 91wait for result",
    "sampleCount" : 3,
    "errorCount" : 0,
    "errorPct" : 0.0,
    "meanResTime" : 306.6666666666667,
    "medianResTime" : 300.0,
    "minResTime" : 271.0,
    "maxResTime" : 349.0,
    "pct1ResTime" : 349.0,
    "pct2ResTime" : 349.0,
    "pct3ResTime" : 349.0,
    "throughput" : 2.798507462686567,
    "receivedKBytesPerSec" : 3.7568505130597014,
    "sentKBytesPerSec" : 1.7217379897388059
  },
  "HTTP GET Request 6wait for result" : {
    "transaction" : "HTTP GET Request 6wait for result",
    "sampleCount" : 2,
    "errorCount" : 0,
    "errorPct" : 0.0,
    "meanResTime" : 306.0,
    "medianResTime" : 306.0,
    "minResTime" : 286.0,
    "maxResTime" : 326.0,
    "pct1ResTime" : 326.0,
    "pct2ResTime" : 326.0,
    "pct3ResTime" : 326.0,
    "throughput" : 3.189792663476874,
    "receivedKBytesPerSec" : 5.163165370813397,
    "sentKBytesPerSec" : 1.492100279106858
  },
  "HTTP GET Request 14 wait for result" : {
    "transaction" : "HTTP GET Request 14 wait for result",
    "sampleCount" : 2,
    "errorCount" : 0,
    "errorPct" : 0.0,
    "meanResTime" : 1670.5,
    "medianResTime" : 1670.5,
    "minResTime" : 1059.0,
    "maxResTime" : 2282.0,
    "pct1ResTime" : 2282.0,
    "pct2ResTime" : 2282.0,
    "pct3ResTime" : 2282.0,
    "throughput" : 0.5924170616113744,
    "receivedKBytesPerSec" : 0.9172629406101896,
    "sentKBytesPerSec" : 0.2771169653436019
  },
  "HTTP GET Request 11 wait for result" : {
    "transaction" : "HTTP GET Request 11 wait for result",
    "sampleCount" : 4,
    "errorCount" : 0,
    "errorPct" : 0.0,
    "meanResTime" : 852.0,
    "medianResTime" : 849.5,
    "minResTime" : 746.0,
    "maxResTime" : 963.0,
    "pct1ResTime" : 963.0,
    "pct2ResTime" : 963.0,
    "pct3ResTime" : 963.0,
    "throughput" : 1.1484352569623888,
    "receivedKBytesPerSec" : 1.8162997057134653,
    "sentKBytesPerSec" : 0.5372075078954924
  },
  "RESOLVED_VULNERABILITIES - HTTP POST Request 90 for running query" : {
    "transaction" : "RESOLVED_VULNERABILITIES - HTTP POST Request 90 for running query",
    "sampleCount" : 3,
    "errorCount" : 0,
    "errorPct" : 0.0,
    "meanResTime" : 814.0,
    "medianResTime" : 664.0,
    "minResTime" : 467.0,
    "maxResTime" : 1311.0,
    "pct1ResTime" : 1311.0,
    "pct2ResTime" : 1311.0,
    "pct3ResTime" : 1311.0,
    "throughput" : 0.07792005402457079,
    "receivedKBytesPerSec" : 0.10889023174722735,
    "sentKBytesPerSec" : 0.04588456306329706
  },
  "COMPLIANCE_FAILED_RULES_BY_STANDARDS - HTTP POST Request 97 for running query" : {
    "transaction" : "COMPLIANCE_FAILED_RULES_BY_STANDARDS - HTTP POST Request 97 for running query",
    "sampleCount" : 6,
    "errorCount" : 0,
    "errorPct" : 0.0,
    "meanResTime" : 1775.5,
    "medianResTime" : 1993.0,
    "minResTime" : 340.0,
    "maxResTime" : 3609.0,
    "pct1ResTime" : 3609.0,
    "pct2ResTime" : 3609.0,
    "pct3ResTime" : 3609.0,
    "throughput" : 0.07907013520993121,
    "receivedKBytesPerSec" : 0.10957082213173083,
    "sentKBytesPerSec" : 0.04648459120740096
  },
  "HTTP POST Request 12 for running query" : {
    "transaction" : "HTTP POST Request 12 for running query",
    "sampleCount" : 3,
    "errorCount" : 0,
    "errorPct" : 0.0,
    "meanResTime" : 415.6666666666667,
    "medianResTime" : 449.0,
    "minResTime" : 323.0,
    "maxResTime" : 475.0,
    "pct1ResTime" : 475.0,
    "pct2ResTime" : 475.0,
    "pct3ResTime" : 475.0,
    "throughput" : 0.07111701118907643,
    "receivedKBytesPerSec" : 0.10947667510193439,
    "sentKBytesPerSec" : 0.04930964642992604
  },
  "OPEN_VULNERABILITIES - HTTP POST Request 89 for running query" : {
    "transaction" : "OPEN_VULNERABILITIES - HTTP POST Request 89 for running query",
    "sampleCount" : 3,
    "errorCount" : 0,
    "errorPct" : 0.0,
    "meanResTime" : 1421.3333333333335,
    "medianResTime" : 440.0,
    "minResTime" : 415.0,
    "maxResTime" : 3409.0,
    "pct1ResTime" : 3409.0,
    "pct2ResTime" : 3409.0,
    "pct3ResTime" : 3409.0,
    "throughput" : 0.06492663290481755,
    "receivedKBytesPerSec" : 0.08075672666969658,
    "sentKBytesPerSec" : 0.03664804083885209
  },
  "TOP_TO_FIX - HTTP POST Request 88 wait for result" : {
    "transaction" : "TOP_TO_FIX - HTTP POST Request 88 wait for result",
    "sampleCount" : 4,
    "errorCount" : 0,
    "errorPct" : 0.0,
    "meanResTime" : 489.0,
    "medianResTime" : 494.5,
    "minResTime" : 282.0,
    "maxResTime" : 685.0,
    "pct1ResTime" : 685.0,
    "pct2ResTime" : 685.0,
    "pct3ResTime" : 685.0,
    "throughput" : 1.3477088948787064,
    "receivedKBytesPerSec" : 1.8379643278301887,
    "sentKBytesPerSec" : 0.8041505222371967
  },
  "CLOSED_DAILY_VLN_URL -  HTTP POST Request 83wait for result" : {
    "transaction" : "CLOSED_DAILY_VLN_URL -  HTTP POST Request 83wait for result",
    "sampleCount" : 2,
    "errorCount" : 0,
    "errorPct" : 0.0,
    "meanResTime" : 286.0,
    "medianResTime" : 286.0,
    "minResTime" : 281.0,
    "maxResTime" : 291.0,
    "pct1ResTime" : 291.0,
    "pct2ResTime" : 291.0,
    "pct3ResTime" : 291.0,
    "throughput" : 2.1739130434782608,
    "receivedKBytesPerSec" : 3.0963400135869565,
    "sentKBytesPerSec" : 1.3056216032608694
  },
  "HTTP GET Request 1 for result" : {
    "transaction" : "HTTP GET Request 1 for result",
    "sampleCount" : 4,
    "errorCount" : 0,
    "errorPct" : 0.0,
    "meanResTime" : 287.75,
    "medianResTime" : 281.0,
    "minResTime" : 268.0,
    "maxResTime" : 321.0,
    "pct1ResTime" : 321.0,
    "pct2ResTime" : 321.0,
    "pct3ResTime" : 321.0,
    "throughput" : 0.04688232536333802,
    "receivedKBytesPerSec" : 0.061510160278949844,
    "sentKBytesPerSec" : 0.02371586380684482
  },
  "HTTP GET Request 1wait for result" : {
    "transaction" : "HTTP GET Request 1wait for result",
    "sampleCount" : 2,
    "errorCount" : 0,
    "errorPct" : 0.0,
    "meanResTime" : 305.0,
    "medianResTime" : 305.0,
    "minResTime" : 287.0,
    "maxResTime" : 323.0,
    "pct1ResTime" : 323.0,
    "pct2ResTime" : 323.0,
    "pct3ResTime" : 323.0,
    "throughput" : 2.7472527472527473,
    "receivedKBytesPerSec" : 4.449529962225275,
    "sentKBytesPerSec" : 1.2850918612637363
  },
  "VLN_BY_SEVERITY - HTTP POST Request 84 wait for result" : {
    "transaction" : "VLN_BY_SEVERITY - HTTP POST Request 84 wait for result",
    "sampleCount" : 2,
    "errorCount" : 0,
    "errorPct" : 0.0,
    "meanResTime" : 649.0,
    "medianResTime" : 649.0,
    "minResTime" : 311.0,
    "maxResTime" : 987.0,
    "pct1ResTime" : 987.0,
    "pct2ResTime" : 987.0,
    "pct3ResTime" : 987.0,
    "throughput" : 1.2091898428053203,
    "receivedKBytesPerSec" : 1.725221055018138,
    "sentKBytesPerSec" : 0.7238607164449818
  },
  "HTTP GET Request 8wait for result" : {
    "transaction" : "HTTP GET Request 8wait for result",
    "sampleCount" : 3,
    "errorCount" : 0,
    "errorPct" : 0.0,
    "meanResTime" : 1063.3333333333333,
    "medianResTime" : 1270.0,
    "minResTime" : 288.0,
    "maxResTime" : 1632.0,
    "pct1ResTime" : 1632.0,
    "pct2ResTime" : 1632.0,
    "pct3ResTime" : 1632.0,
    "throughput" : 0.9247842170160296,
    "receivedKBytesPerSec" : 1.4883245992601726,
    "sentKBytesPerSec" : 0.4325894921393341
  },
  "HTTP GET Request 10 wait for result" : {
    "transaction" : "HTTP GET Request 10 wait for result",
    "sampleCount" : 3,
    "errorCount" : 0,
    "errorPct" : 0.0,
    "meanResTime" : 282.6666666666667,
    "medianResTime" : 269.0,
    "minResTime" : 267.0,
    "maxResTime" : 312.0,
    "pct1ResTime" : 312.0,
    "pct2ResTime" : 312.0,
    "pct3ResTime" : 312.0,
    "throughput" : 3.401360544217687,
    "receivedKBytesPerSec" : 5.362236040249433,
    "sentKBytesPerSec" : 1.5910661139455782
  },
  "HTTP GET Request 2 wait for result" : {
    "transaction" : "HTTP GET Request 2 wait for result",
    "sampleCount" : 14,
    "errorCount" : 0,
    "errorPct" : 0.0,
    "meanResTime" : 781.9999999999999,
    "medianResTime" : 276.0,
    "minResTime" : 261.0,
    "maxResTime" : 3420.0,
    "pct1ResTime" : 3322.5,
    "pct2ResTime" : 3420.0,
    "pct3ResTime" : 3420.0,
    "throughput" : 1.2029558343357964,
    "receivedKBytesPerSec" : 2.0641399671335283,
    "sentKBytesPerSec" : 0.5627107857879361
  },
  "COMPLIANCE_TOP_FAILED_RULES - HTTP POST Request 98 for running query" : {
    "transaction" : "COMPLIANCE_TOP_FAILED_RULES - HTTP POST Request 98 for running query",
    "sampleCount" : 5,
    "errorCount" : 0,
    "errorPct" : 0.0,
    "meanResTime" : 685.6,
    "medianResTime" : 405.0,
    "minResTime" : 372.0,
    "maxResTime" : 1666.0,
    "pct1ResTime" : 1666.0,
    "pct2ResTime" : 1666.0,
    "pct3ResTime" : 1666.0,
    "throughput" : 0.0801012479774435,
    "receivedKBytesPerSec" : 0.11099967859374249,
    "sentKBytesPerSec" : 0.04630853398695952
  },
  "HTTP GET Request 8 for result" : {
    "transaction" : "HTTP GET Request 8 for result",
    "sampleCount" : 4,
    "errorCount" : 0,
    "errorPct" : 0.0,
    "meanResTime" : 638.5,
    "medianResTime" : 303.0,
    "minResTime" : 282.0,
    "maxResTime" : 1666.0,
    "pct1ResTime" : 1666.0,
    "pct2ResTime" : 1666.0,
    "pct3ResTime" : 1666.0,
    "throughput" : 0.05770756690471038,
    "receivedKBytesPerSec" : 0.07576935908533507,
    "sentKBytesPerSec" : 0.028121167856885235
  },
  "HTTP GET Request 13 wait for result" : {
    "transaction" : "HTTP GET Request 13 wait for result",
    "sampleCount" : 3,
    "errorCount" : 0,
    "errorPct" : 0.0,
    "meanResTime" : 2130.3333333333335,
    "medianResTime" : 2154.0,
    "minResTime" : 934.0,
    "maxResTime" : 3303.0,
    "pct1ResTime" : 3303.0,
    "pct2ResTime" : 3303.0,
    "pct3ResTime" : 3303.0,
    "throughput" : 0.4623208506703652,
    "receivedKBytesPerSec" : 0.7419406880875328,
    "sentKBytesPerSec" : 0.21626141354600092
  },
  "COUNTS - HTTP POST Request 81wait for result" : {
    "transaction" : "COUNTS - HTTP POST Request 81wait for result",
    "sampleCount" : 3,
    "errorCount" : 0,
    "errorPct" : 0.0,
    "meanResTime" : 1611.0,
    "medianResTime" : 1176.0,
    "minResTime" : 315.0,
    "maxResTime" : 3342.0,
    "pct1ResTime" : 3342.0,
    "pct2ResTime" : 3342.0,
    "pct3ResTime" : 3342.0,
    "throughput" : 0.5434782608695652,
    "receivedKBytesPerSec" : 0.7724043251811595,
    "sentKBytesPerSec" : 0.3104831861413044
  },
  "NEW_DAILY_VLN - HTTP POST Request 82wait for result" : {
    "transaction" : "NEW_DAILY_VLN - HTTP POST Request 82wait for result",
    "sampleCount" : 3,
    "errorCount" : 0,
    "errorPct" : 0.0,
    "meanResTime" : 1639.3333333333335,
    "medianResTime" : 1128.0,
    "minResTime" : 293.0,
    "maxResTime" : 3497.0,
    "pct1ResTime" : 3497.0,
    "pct2ResTime" : 3497.0,
    "pct3ResTime" : 3497.0,
    "throughput" : 0.5360014293371449,
    "receivedKBytesPerSec" : 0.7582884804359478,
    "sentKBytesPerSec" : 0.31877428756476683
  },
  "CLOSED_DAILY_VLN_URL - HTTP POST Request 83 for running query" : {
    "transaction" : "CLOSED_DAILY_VLN_URL - HTTP POST Request 83 for running query",
    "sampleCount" : 4,
    "errorCount" : 0,
    "errorPct" : 0.0,
    "meanResTime" : 2826.75,
    "medianResTime" : 2769.0,
    "minResTime" : 356.0,
    "maxResTime" : 5413.0,
    "pct1ResTime" : 5413.0,
    "pct2ResTime" : 5413.0,
    "pct3ResTime" : 5413.0,
    "throughput" : 0.0502746251398263,
    "receivedKBytesPerSec" : 0.07025682478036273,
    "sentKBytesPerSec" : 0.02847586189560474
  },
  "NET_NEW - HTTP POST Request 85 for running query" : {
    "transaction" : "NET_NEW - HTTP POST Request 85 for running query",
    "sampleCount" : 4,
    "errorCount" : 0,
    "errorPct" : 0.0,
    "meanResTime" : 654.25,
    "medianResTime" : 419.0,
    "minResTime" : 341.0,
    "maxResTime" : 1438.0,
    "pct1ResTime" : 1438.0,
    "pct2ResTime" : 1438.0,
    "pct3ResTime" : 1438.0,
    "throughput" : 0.054779512462339086,
    "receivedKBytesPerSec" : 0.07655222884141331,
    "sentKBytesPerSec" : 0.029476085319090663
  },
  "COMPLIANCE_TOP_FAILED_RULES - HTTP POST Request 98 wait for result" : {
    "transaction" : "COMPLIANCE_TOP_FAILED_RULES - HTTP POST Request 98 wait for result",
    "sampleCount" : 4,
    "errorCount" : 0,
    "errorPct" : 0.0,
    "meanResTime" : 1353.0,
    "medianResTime" : 1388.5,
    "minResTime" : 966.0,
    "maxResTime" : 1669.0,
    "pct1ResTime" : 1669.0,
    "pct2ResTime" : 1669.0,
    "pct3ResTime" : 1669.0,
    "throughput" : 0.7226738934056007,
    "receivedKBytesPerSec" : 0.9758567637759711,
    "sentKBytesPerSec" : 0.44249661246612465
  },
  "COMPLIANCE_TABLE_BY_SECTIONS - HTTP POST Request 94 wait for result" : {
    "transaction" : "COMPLIANCE_TABLE_BY_SECTIONS - HTTP POST Request 94 wait for result",
    "sampleCount" : 3,
    "errorCount" : 0,
    "errorPct" : 0.0,
    "meanResTime" : 280.3333333333333,
    "medianResTime" : 280.0,
    "minResTime" : 277.0,
    "maxResTime" : 284.0,
    "pct1ResTime" : 284.0,
    "pct2ResTime" : 284.0,
    "pct3ResTime" : 284.0,
    "throughput" : 3.303964757709251,
    "receivedKBytesPerSec" : 4.434325096365638,
    "sentKBytesPerSec" : 2.042392276982379
  },
  "NET_NEW - HTTP POST Request 85 wait for result" : {
    "transaction" : "NET_NEW - HTTP POST Request 85 wait for result",
    "sampleCount" : 3,
    "errorCount" : 0,
    "errorPct" : 0.0,
    "meanResTime" : 529.3333333333334,
    "medianResTime" : 305.0,
    "minResTime" : 296.0,
    "maxResTime" : 987.0,
    "pct1ResTime" : 987.0,
    "pct2ResTime" : 987.0,
    "pct3ResTime" : 987.0,
    "throughput" : 1.3333333333333333,
    "receivedKBytesPerSec" : 1.8537326388888888,
    "sentKBytesPerSec" : 0.7630208333333334
  },
  "AVG_CLOSE_TIME - HTTP POST Request 86wait for result" : {
    "transaction" : "AVG_CLOSE_TIME - HTTP POST Request 86wait for result",
    "sampleCount" : 2,
    "errorCount" : 0,
    "errorPct" : 0.0,
    "meanResTime" : 393.0,
    "medianResTime" : 393.0,
    "minResTime" : 287.0,
    "maxResTime" : 499.0,
    "pct1ResTime" : 499.0,
    "pct2ResTime" : 499.0,
    "pct3ResTime" : 499.0,
    "throughput" : 1.7921146953405018,
    "receivedKBytesPerSec" : 2.4930345542114694,
    "sentKBytesPerSec" : 1.0483170922939067
  },
  "HTTP GET Request 5 wait for result" : {
    "transaction" : "HTTP GET Request 5 wait for result",
    "sampleCount" : 3,
    "errorCount" : 0,
    "errorPct" : 0.0,
    "meanResTime" : 1538.0,
    "medianResTime" : 1285.0,
    "minResTime" : 279.0,
    "maxResTime" : 3050.0,
    "pct1ResTime" : 3050.0,
    "pct2ResTime" : 3050.0,
    "pct3ResTime" : 3050.0,
    "throughput" : 0.6404782237403929,
    "receivedKBytesPerSec" : 1.0307696413321947,
    "sentKBytesPerSec" : 0.2995987003629377
  },
  "HTTP POST Request 11 for running query" : {
    "transaction" : "HTTP POST Request 11 for running query",
    "sampleCount" : 3,
    "errorCount" : 0,
    "errorPct" : 0.0,
    "meanResTime" : 705.3333333333334,
    "medianResTime" : 497.0,
    "minResTime" : 323.0,
    "maxResTime" : 1296.0,
    "pct1ResTime" : 1296.0,
    "pct2ResTime" : 1296.0,
    "pct3ResTime" : 1296.0,
    "throughput" : 0.06449116471043467,
    "receivedKBytesPerSec" : 0.10118730921363774,
    "sentKBytesPerSec" : 0.04887221075712627
  },
  "COMPLIANCE_TABLE - HTTP POST Request 93 for running query" : {
    "transaction" : "COMPLIANCE_TABLE - HTTP POST Request 93 for running query",
    "sampleCount" : 6,
    "errorCount" : 0,
    "errorPct" : 0.0,
    "meanResTime" : 674.1666666666666,
    "medianResTime" : 497.0,
    "minResTime" : 381.0,
    "maxResTime" : 1386.0,
    "pct1ResTime" : 1386.0,
    "pct2ResTime" : 1386.0,
    "pct3ResTime" : 1386.0,
    "throughput" : 0.06912522033663983,
    "receivedKBytesPerSec" : 0.09578973404071475,
    "sentKBytesPerSec" : 0.0395579874192099
  },
  "HTTP POST Request 9 for running query" : {
    "transaction" : "HTTP POST Request 9 for running query",
    "sampleCount" : 4,
    "errorCount" : 0,
    "errorPct" : 0.0,
    "meanResTime" : 686.5,
    "medianResTime" : 664.0,
    "minResTime" : 346.0,
    "maxResTime" : 1072.0,
    "pct1ResTime" : 1072.0,
    "pct2ResTime" : 1072.0,
    "pct3ResTime" : 1072.0,
    "throughput" : 0.05831243804303458,
    "receivedKBytesPerSec" : 0.0892766843183276,
    "sentKBytesPerSec" : 0.04008980115458627
  },
  "HTTP POST Request 10 for running query" : {
    "transaction" : "HTTP POST Request 10 for running query",
    "sampleCount" : 3,
    "errorCount" : 0,
    "errorPct" : 0.0,
    "meanResTime" : 813.3333333333334,
    "medianResTime" : 429.0,
    "minResTime" : 318.0,
    "maxResTime" : 1693.0,
    "pct1ResTime" : 1693.0,
    "pct2ResTime" : 1693.0,
    "pct3ResTime" : 1693.0,
    "throughput" : 0.06321378903451473,
    "receivedKBytesPerSec" : 0.09846288428715917,
    "sentKBytesPerSec" : 0.04679301961734587
  },
  "HTTP POST Request 2 for running query" : {
    "transaction" : "HTTP POST Request 2 for running query",
    "sampleCount" : 4,
    "errorCount" : 0,
    "errorPct" : 0.0,
    "meanResTime" : 620.0,
    "medianResTime" : 450.0,
    "minResTime" : 336.0,
    "maxResTime" : 1244.0,
    "pct1ResTime" : 1244.0,
    "pct2ResTime" : 1244.0,
    "pct3ResTime" : 1244.0,
    "throughput" : 0.046763388942796684,
    "receivedKBytesPerSec" : 0.07992931786829091,
    "sentKBytesPerSec" : 0.06891206436980488
  },
  "COMPLIANCE_TABLE -  HTTP POST Request 93wait for result" : {
    "transaction" : "COMPLIANCE_TABLE -  HTTP POST Request 93wait for result",
    "sampleCount" : 3,
    "errorCount" : 0,
    "errorPct" : 0.0,
    "meanResTime" : 1635.0,
    "medianResTime" : 1003.0,
    "minResTime" : 482.0,
    "maxResTime" : 3420.0,
    "pct1ResTime" : 3420.0,
    "pct2ResTime" : 3420.0,
    "pct3ResTime" : 3420.0,
    "throughput" : 0.6018054162487463,
    "receivedKBytesPerSec" : 0.8078924272818455,
    "sentKBytesPerSec" : 0.36496207372116346
  },
  "COMPLIANCE_STANDARDS - HTTP POST Request 96 for running query" : {
    "transaction" : "COMPLIANCE_STANDARDS - HTTP POST Request 96 for running query",
    "sampleCount" : 6,
    "errorCount" : 0,
    "errorPct" : 0.0,
    "meanResTime" : 938.6666666666666,
    "medianResTime" : 367.0,
    "minResTime" : 342.0,
    "maxResTime" : 3714.0,
    "pct1ResTime" : 3714.0,
    "pct2ResTime" : 3714.0,
    "pct3ResTime" : 3714.0,
    "throughput" : 0.08024286841506961,
    "receivedKBytesPerSec" : 0.11119592800877323,
    "sentKBytesPerSec" : 0.04584187306915598
  },
  "HTTP GET Request 5 for result" : {
    "transaction" : "HTTP GET Request 5 for result",
    "sampleCount" : 4,
    "errorCount" : 0,
    "errorPct" : 0.0,
    "meanResTime" : 450.5,
    "medianResTime" : 284.5,
    "minResTime" : 270.0,
    "maxResTime" : 963.0,
    "pct1ResTime" : 963.0,
    "pct2ResTime" : 963.0,
    "pct3ResTime" : 963.0,
    "throughput" : 0.05519449158973934,
    "receivedKBytesPerSec" : 0.07242929499385961,
    "sentKBytesPerSec" : 0.026896534475859307
  },
  "HTTP POST Request 8 for running query" : {
    "transaction" : "HTTP POST Request 8 for running query",
    "sampleCount" : 4,
    "errorCount" : 0,
    "errorPct" : 0.0,
    "meanResTime" : 1052.75,
    "medianResTime" : 368.5,
    "minResTime" : 317.0,
    "maxResTime" : 3157.0,
    "pct1ResTime" : 3157.0,
    "pct2ResTime" : 3157.0,
    "pct3ResTime" : 3157.0,
    "throughput" : 0.05506153126118437,
    "receivedKBytesPerSec" : 0.08766021615092366,
    "sentKBytesPerSec" : 0.043554531564022794
  },
  "HTTP GET Request 10 for result" : {
    "transaction" : "HTTP GET Request 10 for result",
    "sampleCount" : 3,
    "errorCount" : 0,
    "errorPct" : 0.0,
    "meanResTime" : 292.6666666666667,
    "medianResTime" : 292.0,
    "minResTime" : 290.0,
    "maxResTime" : 296.0,
    "pct1ResTime" : 296.0,
    "pct2ResTime" : 296.0,
    "pct3ResTime" : 296.0,
    "throughput" : 0.06453555909306027,
    "receivedKBytesPerSec" : 0.09010189223637224,
    "sentKBytesPerSec" : 0.03144848045648152
  },
  "HTTP GET Request 2 for result" : {
    "transaction" : "HTTP GET Request 2 for result",
    "sampleCount" : 4,
    "errorCount" : 0,
    "errorPct" : 0.0,
    "meanResTime" : 688.25,
    "medianResTime" : 647.0,
    "minResTime" : 281.0,
    "maxResTime" : 1178.0,
    "pct1ResTime" : 1178.0,
    "pct2ResTime" : 1178.0,
    "pct3ResTime" : 1178.0,
    "throughput" : 0.054338966472857686,
    "receivedKBytesPerSec" : 0.07532633096506006,
    "sentKBytesPerSec" : 0.026479633076128894
  },
  "NONCOMPLIANT_ASSETS_OVERTIME - HTTP POST Request 100 for running query" : {
    "transaction" : "NONCOMPLIANT_ASSETS_OVERTIME - HTTP POST Request 100 for running query",
    "sampleCount" : 5,
    "errorCount" : 0,
    "errorPct" : 0.0,
    "meanResTime" : 654.2,
    "medianResTime" : 383.0,
    "minResTime" : 360.0,
    "maxResTime" : 1606.0,
    "pct1ResTime" : 1606.0,
    "pct2ResTime" : 1606.0,
    "pct3ResTime" : 1606.0,
    "throughput" : 0.09003655484126556,
    "receivedKBytesPerSec" : 0.12476745246069904,
    "sentKBytesPerSec" : 0.05214030959069382
  },
  "HTTP GET Request 14 for result" : {
    "transaction" : "HTTP GET Request 14 for result",
    "sampleCount" : 3,
    "errorCount" : 0,
    "errorPct" : 0.0,
    "meanResTime" : 616.3333333333334,
    "medianResTime" : 298.0,
    "minResTime" : 284.0,
    "maxResTime" : 1267.0,
    "pct1ResTime" : 1267.0,
    "pct2ResTime" : 1267.0,
    "pct3ResTime" : 1267.0,
    "throughput" : 0.08530482256596907,
    "receivedKBytesPerSec" : 0.25258224806642404,
    "sentKBytesPerSec" : 0.041569439902752504
  },
  "OPEN_VULNERABILITIES - HTTP POST Request 89wait for result" : {
    "transaction" : "OPEN_VULNERABILITIES - HTTP POST Request 89wait for result",
    "sampleCount" : 5,
    "errorCount" : 0,
    "errorPct" : 0.0,
    "meanResTime" : 1255.8,
    "medianResTime" : 746.0,
    "minResTime" : 307.0,
    "maxResTime" : 3028.0,
    "pct1ResTime" : 3028.0,
    "pct2ResTime" : 3028.0,
    "pct3ResTime" : 3028.0,
    "throughput" : 0.6577216521967902,
    "receivedKBytesPerSec" : 0.9088634158774006,
    "sentKBytesPerSec" : 0.3937337624967114
  },
  "NONCOMPLIANT_ASSETS_OVERTIME - HTTP POST Request 100 wait for result" : {
    "transaction" : "NONCOMPLIANT_ASSETS_OVERTIME - HTTP POST Request 100 wait for result",
    "sampleCount" : 7,
    "errorCount" : 0,
    "errorPct" : 0.0,
    "meanResTime" : 752.0,
    "medianResTime" : 811.0,
    "minResTime" : 284.0,
    "maxResTime" : 1172.0,
    "pct1ResTime" : 1172.0,
    "pct2ResTime" : 1172.0,
    "pct3ResTime" : 1172.0,
    "throughput" : 1.287001287001287,
    "receivedKBytesPerSec" : 1.7507742117117118,
    "sentKBytesPerSec" : 0.789293758043758
  },
  "HTTP POST Request 1 for running query" : {
    "transaction" : "HTTP POST Request 1 for running query",
    "sampleCount" : 4,
    "errorCount" : 0,
    "errorPct" : 0.0,
    "meanResTime" : 1631.0,
    "medianResTime" : 1270.5,
    "minResTime" : 1100.0,
    "maxResTime" : 2883.0,
    "pct1ResTime" : 2883.0,
    "pct2ResTime" : 2883.0,
    "pct3ResTime" : 2883.0,
    "throughput" : 0.044975151228946006,
    "receivedKBytesPerSec" : 0.0716791472711327,
    "sentKBytesPerSec" : 0.035707810497200294
  },
  "TOP_NONCOMPLIANT_ASSETS - HTTP POST Request 99wait for result" : {
    "transaction" : "TOP_NONCOMPLIANT_ASSETS - HTTP POST Request 99wait for result",
    "sampleCount" : 5,
    "errorCount" : 0,
    "errorPct" : 0.0,
    "meanResTime" : 286.8,
    "medianResTime" : 286.0,
    "minResTime" : 270.0,
    "maxResTime" : 305.0,
    "pct1ResTime" : 305.0,
    "pct2ResTime" : 305.0,
    "pct3ResTime" : 305.0,
    "throughput" : 3.3222591362126246,
    "receivedKBytesPerSec" : 4.499974044850498,
    "sentKBytesPerSec" : 2.0212572674418605
  },
  "HTTP GET Request 11 for result" : {
    "transaction" : "HTTP GET Request 11 for result",
    "sampleCount" : 3,
    "errorCount" : 0,
    "errorPct" : 0.0,
    "meanResTime" : 276.6666666666667,
    "medianResTime" : 277.0,
    "minResTime" : 267.0,
    "maxResTime" : 286.0,
    "pct1ResTime" : 286.0,
    "pct2ResTime" : 286.0,
    "pct3ResTime" : 286.0,
    "throughput" : 0.0714694110920526,
    "receivedKBytesPerSec" : 0.09489704682437583,
    "sentKBytesPerSec" : 0.03482737903802173
  },
  "HTTP GET Request 12 wait for result" : {
    "transaction" : "HTTP GET Request 12 wait for result",
    "sampleCount" : 3,
    "errorCount" : 0,
    "errorPct" : 0.0,
    "meanResTime" : 268.6666666666667,
    "medianResTime" : 267.0,
    "minResTime" : 264.0,
    "maxResTime" : 275.0,
    "pct1ResTime" : 275.0,
    "pct2ResTime" : 275.0,
    "pct3ResTime" : 275.0,
    "throughput" : 3.4965034965034967,
    "receivedKBytesPerSec" : 5.442799388111888,
    "sentKBytesPerSec" : 1.6355714597902098
  },
  "TOP_TO_FIX - HTTP POST Request 88 for running query" : {
    "transaction" : "TOP_TO_FIX - HTTP POST Request 88 for running query",
    "sampleCount" : 3,
    "errorCount" : 0,
    "errorPct" : 0.0,
    "meanResTime" : 2568.6666666666665,
    "medianResTime" : 2209.0,
    "minResTime" : 1295.0,
    "maxResTime" : 4202.0,
    "pct1ResTime" : 4202.0,
    "pct2ResTime" : 4202.0,
    "pct3ResTime" : 4202.0,
    "throughput" : 0.062189054726368154,
    "receivedKBytesPerSec" : 0.08690677472014925,
    "sentKBytesPerSec" : 0.034981343283582086
  },
  "AVG_CLOSE_TIME - HTTP POST Request 86 for running query" : {
    "transaction" : "AVG_CLOSE_TIME - HTTP POST Request 86 for running query",
    "sampleCount" : 4,
    "errorCount" : 0,
    "errorPct" : 0.0,
    "meanResTime" : 1130.75,
    "medianResTime" : 509.5,
    "minResTime" : 458.0,
    "maxResTime" : 3046.0,
    "pct1ResTime" : 3046.0,
    "pct2ResTime" : 3046.0,
    "pct3ResTime" : 3046.0,
    "throughput" : 0.05670220004536176,
    "receivedKBytesPerSec" : 0.07923910963370379,
    "sentKBytesPerSec" : 0.031230508618734408
  },
  "COMPLIANCE_SUNBURST - HTTP POST Request 92wait for result" : {
    "transaction" : "COMPLIANCE_SUNBURST - HTTP POST Request 92wait for result",
    "sampleCount" : 3,
    "errorCount" : 0,
    "errorPct" : 0.0,
    "meanResTime" : 283.6666666666667,
    "medianResTime" : 285.0,
    "minResTime" : 281.0,
    "maxResTime" : 285.0,
    "pct1ResTime" : 285.0,
    "pct2ResTime" : 285.0,
    "pct3ResTime" : 285.0,
    "throughput" : 2.944062806673209,
    "receivedKBytesPerSec" : 3.951292627576055,
    "sentKBytesPerSec" : 1.8112886408243378
  },
  "HTTP GET Request 13 for result" : {
    "transaction" : "HTTP GET Request 13 for result",
    "sampleCount" : 3,
    "errorCount" : 0,
    "errorPct" : 0.0,
    "meanResTime" : 900.0,
    "medianResTime" : 860.0,
    "minResTime" : 751.0,
    "maxResTime" : 1089.0,
    "pct1ResTime" : 1089.0,
    "pct2ResTime" : 1089.0,
    "pct3ResTime" : 1089.0,
    "throughput" : 0.078003120124805,
    "receivedKBytesPerSec" : 0.10367406883775351,
    "sentKBytesPerSec" : 0.03801128607644306
  },
  "VLN_BY_SEVERITY HTTP POST Request 84 for running query" : {
    "transaction" : "VLN_BY_SEVERITY HTTP POST Request 84 for running query",
    "sampleCount" : 4,
    "errorCount" : 0,
    "errorPct" : 0.0,
    "meanResTime" : 1467.0,
    "medianResTime" : 696.5,
    "minResTime" : 415.0,
    "maxResTime" : 4060.0,
    "pct1ResTime" : 4060.0,
    "pct2ResTime" : 4060.0,
    "pct3ResTime" : 4060.0,
    "throughput" : 0.05082915051782197,
    "receivedKBytesPerSec" : 0.0710317523349641,
    "sentKBytesPerSec" : 0.02869067285087998
  },
  "PUBLISHED_AGE - HTTP POST Request 87 wait for result" : {
    "transaction" : "PUBLISHED_AGE - HTTP POST Request 87 wait for result",
    "sampleCount" : 2,
    "errorCount" : 0,
    "errorPct" : 0.0,
    "meanResTime" : 287.0,
    "medianResTime" : 287.0,
    "minResTime" : 284.0,
    "maxResTime" : 290.0,
    "pct1ResTime" : 290.0,
    "pct2ResTime" : 290.0,
    "pct3ResTime" : 290.0,
    "throughput" : 2.1810250817884405,
    "receivedKBytesPerSec" : 3.0926254089422027,
    "sentKBytesPerSec" : 1.2736845692475462
  },
  "COUNTS - HTTP POST Request 81 for running query" : {
    "transaction" : "COUNTS - HTTP POST Request 81 for running query",
    "sampleCount" : 4,
    "errorCount" : 0,
    "errorPct" : 0.0,
    "meanResTime" : 1637.0,
    "medianResTime" : 1237.0,
    "minResTime" : 1192.0,
    "maxResTime" : 2882.0,
    "pct1ResTime" : 2882.0,
    "pct2ResTime" : 2882.0,
    "pct3ResTime" : 2882.0,
    "throughput" : 0.04496857820597858,
    "receivedKBytesPerSec" : 0.06284183145776889,
    "sentKBytesPerSec" : 0.024153044934851774
  },
  "COMPLIANCE_SUNBURST - HTTP POST Request 91 for running query" : {
    "transaction" : "COMPLIANCE_SUNBURST - HTTP POST Request 91 for running query",
    "sampleCount" : 6,
    "errorCount" : 0,
    "errorPct" : 0.0,
    "meanResTime" : 3076.6666666666665,
    "medianResTime" : 2089.5,
    "minResTime" : 1236.0,
    "maxResTime" : 6904.0,
    "pct1ResTime" : 6904.0,
    "pct2ResTime" : 6904.0,
    "pct3ResTime" : 6904.0,
    "throughput" : 0.06258670866930226,
    "receivedKBytesPerSec" : 0.08672904257982413,
    "sentKBytesPerSec" : 0.03636630044749496
  },
  "Total" : {
    "transaction" : "Total",
    "sampleCount" : 279,
    "errorCount" : 0,
    "errorPct" : 0.0,
    "meanResTime" : 984.8028673835122,
    "medianResTime" : 439.0,
    "minResTime" : 261.0,
    "maxResTime" : 6904.0,
    "pct1ResTime" : 2882.0,
    "pct2ResTime" : 3609.0,
    "pct3ResTime" : 5436.5999999999985,
    "throughput" : 2.720093594618309,
    "receivedKBytesPerSec" : 3.960186107658185,
    "sentKBytesPerSec" : 1.5960136979623674
  },
  "COMPLIANCE_TABLE_BY_SECTIONS - HTTP POST Request 94 for running query" : {
    "transaction" : "COMPLIANCE_TABLE_BY_SECTIONS - HTTP POST Request 94 for running query",
    "sampleCount" : 6,
    "errorCount" : 0,
    "errorPct" : 0.0,
    "meanResTime" : 1937.0,
    "medianResTime" : 459.5,
    "minResTime" : 402.0,
    "maxResTime" : 5531.0,
    "pct1ResTime" : 5531.0,
    "pct2ResTime" : 5531.0,
    "pct3ResTime" : 5531.0,
    "throughput" : 0.0734340195334492,
    "receivedKBytesPerSec" : 0.10176061886519962,
    "sentKBytesPerSec" : 0.042884320000979116
  },
  "COMPLIANCE_TREND - HTTP POST Request 95 for running query" : {
    "transaction" : "COMPLIANCE_TREND - HTTP POST Request 95 for running query",
    "sampleCount" : 6,
    "errorCount" : 0,
    "errorPct" : 0.0,
    "meanResTime" : 501.6666666666667,
    "medianResTime" : 501.0,
    "minResTime" : 375.0,
    "maxResTime" : 630.0,
    "pct1ResTime" : 630.0,
    "pct2ResTime" : 630.0,
    "pct3ResTime" : 630.0,
    "throughput" : 0.07414913863417287,
    "receivedKBytesPerSec" : 0.10275158957215946,
    "sentKBytesPerSec" : 0.04243300316369658
  },
  "PUBLISHED_AGE - HTTP POST Request 87 for running query" : {
    "transaction" : "PUBLISHED_AGE - HTTP POST Request 87 for running query",
    "sampleCount" : 4,
    "errorCount" : 0,
    "errorPct" : 0.0,
    "meanResTime" : 1341.25,
    "medianResTime" : 421.5,
    "minResTime" : 379.0,
    "maxResTime" : 4143.0,
    "pct1ResTime" : 4143.0,
    "pct2ResTime" : 4143.0,
    "pct3ResTime" : 4143.0,
    "throughput" : 0.056984115677754826,
    "receivedKBytesPerSec" : 0.07963307571764372,
    "sentKBytesPerSec" : 0.031330133912671844
  },
  "RESOLVED_VULNERABILITIES - HTTP POST Request 90 wait for result" : {
    "transaction" : "RESOLVED_VULNERABILITIES - HTTP POST Request 90 wait for result",
    "sampleCount" : 4,
    "errorCount" : 0,
    "errorPct" : 0.0,
    "meanResTime" : 811.5,
    "medianResTime" : 489.5,
    "minResTime" : 282.0,
    "maxResTime" : 1985.0,
    "pct1ResTime" : 1985.0,
    "pct2ResTime" : 1985.0,
    "pct3ResTime" : 1985.0,
    "throughput" : 0.9352349777881693,
    "receivedKBytesPerSec" : 1.275673296118775,
    "sentKBytesPerSec" : 0.5826952303016133
  },
  "HTTP GET Request 12 for result" : {
    "transaction" : "HTTP GET Request 12 for result",
    "sampleCount" : 3,
    "errorCount" : 0,
    "errorPct" : 0.0,
    "meanResTime" : 712.0,
    "medianResTime" : 836.0,
    "minResTime" : 274.0,
    "maxResTime" : 1026.0,
    "pct1ResTime" : 1026.0,
    "pct2ResTime" : 1026.0,
    "pct3ResTime" : 1026.0,
    "throughput" : 0.07173258093826217,
    "receivedKBytesPerSec" : 0.09526983405862942,
    "sentKBytesPerSec" : 0.034955622937688294
  }
}